LICENSE
MANIFEST.in
README.md
setup.py
michelanglo_api/__init__.py
michelanglo_api/base.py
michelanglo_api/bootstrap_elements.py
michelanglo_api/core.py
michelanglo_api/enums.py
michelanglo_api/page.py
michelanglo_api/progressbar.py
michelanglo_api/prolink.py
michelanglo_api/ss_parser.py
michelanglo_api/table.js
michelanglo_api/table.py
michelanglo_api/venus.py
michelanglo_api.egg-info/PKG-INFO
michelanglo_api.egg-info/SOURCES.txt
michelanglo_api.egg-info/dependency_links.txt
michelanglo_api.egg-info/top_level.txt