Metadata-Version: 2.1
Name: michelanglo-api
Version: 1.1.6
Summary: API to interface with Michelanglo
Home-page: https://github.com/matteoferla/MichelaNGLo-api
Author: Matteo Ferla. [Github](https://github.com/matteoferla)
Author-email: matteo.ferla@gmail.com
License: MIT
Requires: requests
Requires: pandas
Requires: numpy
License-File: LICENSE
